.gitignore
.travis.yml
LICENSE
README.rst
appveyor.yml
requirements.txt
setup.py
binder/postBuild
binder/requirements.txt
binder/tutorial.ipynb
docs/Makefile
docs/make.bat
docs/source/axis-descriptors.rst
docs/source/books-of-histograms.rst
docs/source/conf.py
docs/source/histograms.rst
docs/source/index.rst
docs/source/intro-1.png
docs/source/intro-10.png
docs/source/intro-11.png
docs/source/intro-12.png
docs/source/intro-13.png
docs/source/intro-14.png
docs/source/intro-2.png
docs/source/intro-3.png
docs/source/intro-4.png
docs/source/intro-5.png
docs/source/intro-6.png
docs/source/intro-7.png
docs/source/intro-8.png
docs/source/intro-9.png
docs/source/logo-1000px.png
docs/source/logo-500px.png
docs/source/logo.svg
docs/source/plotting.rst
histbook/__init__.py
histbook/axis.py
histbook/book.py
histbook/export.py
histbook/expr.py
histbook/fill.py
histbook/hist.py
histbook/instr.py
histbook/proj.py
histbook/vega.py
histbook/version.py
histbook.egg-info/PKG-INFO
histbook.egg-info/SOURCES.txt
histbook.egg-info/dependency_links.txt
histbook.egg-info/requires.txt
histbook.egg-info/top_level.txt
histbook/calc/__init__.py
histbook/calc/spark.py
histbook/util/__init__.py
histbook/util/astunparse.py
tests/__init__.py
tests/test_book.py
tests/test_expr.py
tests/test_hist.py
tests/test_proj.py