Metadata-Version: 1.2
Name: histbook
Version: 1.2.4
Summary: Versatile, high-performance histogram toolkit for Numpy.
Home-page: https://github.com/scikit-hep/histbook
Author: Jim Pivarski (DIANA-HEP)
Author-email: pivarski@fnal.gov
Maintainer: Jim Pivarski (DIANA-HEP)
Maintainer-email: pivarski@fnal.gov
License: BSD 3-clause
Download-URL: https://github.com/scikit-hep/histbook/releases
Platform: Any
Classifier: Development Status :: 5 - Production/Stable
Classifier: Intended Audience :: Developers
Classifier: Intended Audience :: Information Technology
Classifier: Intended Audience :: Science/Research
Classifier: License :: OSI Approved :: BSD License
Classifier: Operating System :: MacOS
Classifier: Operating System :: POSIX
Classifier: Operating System :: Unix
Classifier: Programming Language :: Python
Classifier: Programming Language :: Python :: 2.7
Classifier: Programming Language :: Python :: 3.4
Classifier: Programming Language :: Python :: 3.5
Classifier: Programming Language :: Python :: 3.6
Classifier: Programming Language :: Python :: 3.7
Classifier: Topic :: Scientific/Engineering
Classifier: Topic :: Scientific/Engineering :: Information Analysis
Classifier: Topic :: Scientific/Engineering :: Mathematics
Classifier: Topic :: Scientific/Engineering :: Physics
Classifier: Topic :: Software Development
Classifier: Topic :: Utilities
